colored_context_logger/__init__.py
colored_context_logger-0.1.1.dist-info/METADATA
colored_context_logger-0.1.1.dist-info/WHEEL
colored_context_logger-0.1.1.dist-info/top_level.txt
colored_context_logger-0.1.1.dist-info/RECORD
