Metadata-Version: 2.4
Name: colored-context-logger
Version: 0.1.1
Summary: A colored logger with context injection support for Python applications.
Author-email: Your Name <your.email@example.com>
License: MIT
Classifier: Programming Language :: Python :: 3
Classifier: License :: OSI Approved :: MIT License
Classifier: Operating System :: OS Independent
Requires-Python: >=3.8
Requires-Dist: coloredlogs>=15.0.1
